[
  {
    "code": "No authentication/private",
    "description": "Autentique-se usando&nbsp;<span onclick=\"$('#authModal').modal('show');\" class=\"openAuth\">cookies</span>&nbsp;e tente novamente.",
    "trigger": [
      "ERROR: Private video",
      "This video is private",
      "Please sign in or sign up to view this video.",
      "ERROR: This video is only available for registered users"
    ]
  },
  {
    "code": "Members-only content",
    "description": "Autentique-se usando&nbsp;<span onclick=\"$('#authModal').modal('show');\" class=\"openAuth\">cookies</span>&nbsp;e tente novamente.",
    "trigger": [
      "ERROR: Join this channel to get access to members-only content",
      "This video is available to this channel's members on level"
    ]
  },
  {
    "code": "Blocked in country",
    "description": "O uploader bloqueou este vídeo no seu país.",
    "trigger": " The uploader has not made this video available in your country"
  },
  {
    "code": "Blocked",
    "description": "Este vídeo está bloqueado por um motivo não especificado.",
    "trigger": " The video is blocked"
  },
  {
    "code": "Channel unavailable",
    "description": "Este canal não está disponível no momento.",
    "trigger": "This channel is not available"
  },
  {
    "code": "No connection could be made",
    "description": "O servidor ou sua conexão de internet/proxy está fora do ar.",
    "trigger": "getaddrinfo failed"
  },
  {
    "code": "URL not supported",
    "description": "Esta URL não é suportada atualmente pelo YTDL.",
    "trigger": [
      "is not a valid URL",
      "Unsupported URL"
    ]
  },
  {
    "code": "URL not found",
    "description": "Esta é uma URL incorreta ou inexistente.",
    "trigger": "[Errno 11001]"
  },
  {
    "code": "Private or non-existent playlist",
    "description": "Esta playlist não existe ou é&nbsp;<span onclick=\"$('#authModal').modal('show');\" class=\"openAuth\">privada</span>.",
    "trigger": "ERROR: The playlist does not exist"
  },
  {
    "code": "Age restricted video",
    "description": "Para baixar este vídeo, faça login usando&nbsp;<span onclick=\"$('#authModal').modal('show');\" class=\"openAuth\">cookies</span>.",
    "trigger": [
      "ERROR: Sign in to confirm your age",
      "Verify your age"
    ]
  },
  {
    "code": "Embed-only video",
    "description": "Tente usar a URL da página de incorporação.",
    "trigger": "ERROR: Cannot download embed-only video without embedding URL"
  },
  {
    "code": "Possible broken extractor (404)",
    "description": "O YTDL não está funcionando, por favor aguarde uma atualização.",
    "trigger": "HTTP Error 404"
  },
  {
    "code": "Private or removed video",
    "description": "Este vídeo não pode ser extraído.",
    "trigger": "metadata.formats is not iterable"
  },
  {
    "code": "ffmpeg not found",
    "description": "A união de formatos requer ffmpeg.",
    "trigger": "ffmpeg or avconv not found"
  },
  {
    "code": "ffmpeg not found",
    "description": "A conversão para mp3 ou mp4 requer ffmpeg.",
    "trigger": [
      "ffmpeg or avconv could not be found",
      "ffprobe/avprobe and ffmpeg/avconv not found"
    ]
  },
  {
    "code": "Incomplete video ID",
    "description": "A URL que você inseriu está incompleta.",
    "trigger": "Incomplete YouTube ID"
  },
  {
    "code": "Too many requests (429)",
    "description": "Você está sendo limitado pelo serviço.",
    "trigger": "HTTP Error 429"
  },
  {
    "code": "Unable to extract initial data",
    "description": "Por favor, tente novamente em um momento.",
    "trigger": [
      "ERROR: Unable to extract yt initial data",
      "Did not get any data blocks"
      ]
  },
  {
    "code": "No write permission",
    "description": "Sem permissão de escrita na pasta de download.",
    "trigger": "[Errno 95]"
  },
  {
    "code": "Blocked by firewall/program",
    "description": "Verifique seu firewall e/ou configurações de internet.",
    "trigger": "[WinError 10013]"
  },
  {
    "code": "Permission denied",
    "description": "Não foi possível escrever arquivos no local de download.",
    "trigger": "[Errno 13]"
  },
  {
    "code": "SSL verification failed",
    "description": "Desative a configuração 'Validar certificados HTTPS'.",
    "trigger": "<urlopen error [SSL: CERTIFICATE_VERIFY_FAILED] certificate verify failed"
  },
  {
    "code": "Max fragment retries reached",
    "description": "O serviço não respondeu a tempo.",
    "trigger": [
      "giving up after 10 fragment retries",
      "giving up after 10 retries"
    ]
  },
  {
    "code": "Connection timed out",
    "description": "Por favor, tente novamente em um momento.",
    "trigger": [
      "EOF occurred in violation of protocol",
      "[Errno 60]"
    ]
  },
  {
    "code": "No connection could be made",
    "description": "Verifique seu proxy e conexão com a internet.",
    "trigger": "[WinError 10060]"
  },
  {
    "code": "Connection refused",
    "description": "O serviço ou sua internet pode estar fora do ar.",
    "trigger": "[WinError 10061]"
  },
  {
    "code": "Connection reset",
    "description": "A conexão foi fechada pelo host remoto.",
    "trigger": "[WinError 10054]"
  },
  {
    "code": "No space left on device",
    "description": "Você não tem espaço livre em seu disco.",
    "trigger": "[Errno 28]"
  },
  {
    "code": "This video is DRM protected",
    "description": "Faça login ou use um proxy para baixar este vídeo.",
    "trigger": "This video is DRM protected"
  },
  {
    "code": "File in use by another process",
    "description": "Não abra o arquivo enquanto estiver baixando.",
    "trigger": "[WinError 32]"
  },
  {
    "code": "HTTP error 403",
    "description": "Você pode estar com limitação de taxa, tente limpar o cache.",
    "trigger": [
      "HTTP Error 403",
      "Error 403"
    ]
  },
  {
    "code": "HTTP error 400",
    "description": "URL inválida ou extrator quebrado.",
    "trigger": "HTTP Error 400"
  },
  {
    "code": "HTTP error 405",
    "description": "URL inválida ou extrator quebrado.",
    "trigger": "HTTP Error 405"
  },
  {
    "code": "No video found",
    "description": "Este tweet não contém um vídeo.",
    "trigger": "There's no video in this tweet"
  },
  {
    "code": "Binaries missing/corrupted",
    "description": "Por favor, reinicie o aplicativo e desative o antivírus.",
    "trigger": [
      "Command failed with ENOENT: resources\\app.asar.unpacked\\binaries\\youtube-dl.exe",
      "Command failed with ENOENT: binaries/youtube-dl.exe",
      "is not recognized as an internal or external command"
    ]
  },
  {
    "code": "Missing dependency",
    "description": "Por favor, instale <a href=\"https://github.com/ReginaldoHorse/BaixaVideos3000#how-to-use\" target=\"_blank\"> Microsoft Visual C++ 2010</a>",
    "trigger": "3221225781"
  },
  {
    "code": "Video not found",
    "description": "Este vídeo não existe.",
    "trigger": [
      "Video has not been found",
      "does not exist"
    ]
  },
  {
    "code": "Geo-locked content",
    "description": "Tente usar uma VPN ou proxy.",
    "trigger": [
      "bbc.co.uk returned error: geolocation",
      "This video is not available from your location due to geo restriction"
    ]
  },
  {
    "code": "Access forbidden",
    "description": "Permissões insuficientes para acessar a URL de download.",
    "trigger": "Access to this resource is forbidden by access policy"
  },
  {
    "code": "Unknown URL type",
    "description": "Um esquema de URL inválido foi usado, tente usar http/https.",
    "trigger": "urlopen error unknown url type"
  },
  {
    "code": "Download file not found",
    "description": "O arquivo de download foi excluído/movido antes de ser concluído.",
    "trigger": "[WinError 2]"
  },
  {
    "code": "Not premiered yet",
    "description": "Este vídeo ainda não estreou.",
    "trigger": "Premieres in"
  },
  {
    "code": "Copyright claimed",
    "description": "Este vídeo foi bloqueado devido a uma reclamação de direitos autorais.",
    "trigger": "who has blocked it on copyright grounds"
  },
  {
    "code": "Cannot allocate memory",
    "description": "O FFmpeg ficou sem memória, a conversão falhou.",
    "trigger": "Cannot allocate memory"
  },
  {
    "code": "Livestream not started yet",
    "description": "Aguarde o início da transmissão ao vivo.",
    "trigger": "This live event will begin in a few moments."
  },
  {
    "code": "Thumbnail embedding not supported",
    "description": "Apenas mp3 e m4a/mp4 são suportados para incorporação de miniaturas por enquanto.",
    "trigger": "ERROR: Only mp3 and m4a/mp4 are supported for thumbnail embedding for now."
  },
  {
    "code": "SponsorBlock API unreachable",
    "description": "Não foi possível se comunicar com a API do SponsorBlock, por favor tente novamente.",
    "trigger": "ERROR: Unable to communicate with SponsorBlock API"
  }
]
